wuddz_dapp/__init__.py
wuddz_dapp/config.py
wuddz_dapp/dapp.py
wuddz_dapp/docs.py
wuddz_dapp/exchange_api.py
wuddz_dapp-1.0.5.dist-info/METADATA
wuddz_dapp-1.0.5.dist-info/WHEEL
wuddz_dapp-1.0.5.dist-info/entry_points.txt
wuddz_dapp-1.0.5.dist-info/licenses/LICENSE
wuddz_dapp-1.0.5.dist-info/RECORD
