Metadata-Version: 2.4
Name: wuddz-dapp
Version: 1.0.5
Summary: Multi-Purpose ERC20 Dapp, Create Accounts, Check Balances, Make Transactions, Deploy Verify & Interact With Smart Contracts, Swap ERC20 Tokens, Interact With Exchange Using Api Authentication, Convert Crypto To Crypto Value & Get Token Prices In USD
Project-URL: Homepage, https://github.com/wuddz-devs/wuddz-dapp
Author-email: Wuddz-Devs <wuddz_devs@protonmail.com>
License: MIT License
License-File: LICENSE
Keywords: crypto,dapp,erc20,ethereum,exchange,trade,transactions,web3
Classifier: License :: OSI Approved :: MIT License
Classifier: Programming Language :: Python
Classifier: Programming Language :: Python :: 3.7
Classifier: Programming Language :: Python :: 3.8
Classifier: Programming Language :: Python :: 3.9
Classifier: Programming Language :: Python :: 3.10
Requires-Python: >=3.7
Requires-Dist: ccxt
Requires-Dist: pycoingecko
Requires-Dist: requests
Requires-Dist: setuptools
Requires-Dist: web3<=6.13
